is_13ai/__init__.py
is_13ai/is_13.py
is_13ai-0.2.dist-info/METADATA
is_13ai-0.2.dist-info/WHEEL
is_13ai-0.2.dist-info/top_level.txt
is_13ai-0.2.dist-info/RECORD
